pyrser/__init__.py
pyrser/dsl.py
pyrser/error.py
pyrser/fmt.py
pyrser/grammar.py
pyrser/meta.py
pyrser/directives/__init__.py
pyrser/directives/ignore.py
pyrser/directives/trace.py
pyrser/hooks/__init__.py
pyrser/hooks/dump_nodes.py
pyrser/hooks/echo.py
pyrser/hooks/predicate.py
pyrser/hooks/set.py
pyrser/hooks/vars.py
pyrser/parsing/__init__.py
pyrser/parsing/base.py
pyrser/parsing/functors.py
pyrser/parsing/ir.py
pyrser/parsing/node.py
pyrser/parsing/stream.py
pyrser/passes/__init__.py
pyrser/passes/to_dsl.py
pyrser/passes/to_ir.py
pyrser/passes/to_yml.py
pyrser/passes/topython.py
pyrser/type_system/__init__.py
pyrser/type_system/evalctx.py
pyrser/type_system/fun.py
pyrser/type_system/inference.py
pyrser/type_system/scope.py
pyrser/type_system/signature.py
pyrser/type_system/symbol.py
pyrser/type_system/to_fmt.py
pyrser/type_system/translator.py
pyrser/type_system/tuple.py
pyrser/type_system/type.py
pyrser/type_system/type_expr.py
pyrser/type_system/type_name.py
pyrser/type_system/val.py
pyrser/type_system/var.py
pyrser-0.2.0.dist-info/DESCRIPTION.rst
pyrser-0.2.0.dist-info/LICENSE.txt
pyrser-0.2.0.dist-info/METADATA
pyrser-0.2.0.dist-info/RECORD
pyrser-0.2.0.dist-info/WHEEL
pyrser-0.2.0.dist-info/metadata.json
pyrser-0.2.0.dist-info/top_level.txt
