Metadata-Version: 2.0
Name: pyrser
Version: 0.2.0
Summary: Pyrser a pragmatic PEG parsing tool
Home-page: https://github.com/LionelAuroux/pyrser/
Author: Lionel Auroux
Author-email: lionel.auroux@gmail.com
License: GPLv3
Keywords: parse parser parsing peg packrat grammar language
Platform: UNKNOWN
Classifier: Development Status :: 5 - Production/Stable
Classifier: Environment :: Console
Classifier: Intended Audience :: Developers
Classifier: Intended Audience :: Education
Classifier: Intended Audience :: Information Technology
Classifier: Intended Audience :: Science/Research
Classifier: License :: OSI Approved :: GNU General Public License v3 (GPLv3)
Classifier: License :: OSI Approved :: GNU General Public License v3 or later (GPLv3+)
Classifier: Operating System :: OS Independent
Classifier: Programming Language :: Python :: 3
Classifier: Programming Language :: Python :: 3.4
Classifier: Programming Language :: Python :: 3.5
Classifier: Topic :: Scientific/Engineering :: Information Analysis
Classifier: Topic :: Software Development :: Code Generators
Classifier: Topic :: Software Development :: Compilers
Classifier: Topic :: Software Development :: Libraries :: Python Modules
Classifier: Topic :: Text Processing :: General
Provides-Extra: DOC
Requires-Dist: Sphinx; extra == 'DOC'
Requires-Dist: sphinxcontrib-programoutput; extra == 'DOC'
